fastapi_playbook/__init__.py
fastapi_playbook/config.py
fastapi_playbook/models.py
fastapi_playbook/repository.py
fastapi_playbook/routes.py
fastapi_playbook-0.1.0.dist-info/METADATA
fastapi_playbook-0.1.0.dist-info/WHEEL
fastapi_playbook-0.1.0.dist-info/RECORD
